aihordeclient/__init__.py
aihordeclient/default_styles.json
aihordeclient/py.typed
aihordeclient/translation_tool.py
aihordeclient-0.4.dist-info/licenses/LICENSE
aihordeclient-0.4.dist-info/WHEEL
aihordeclient-0.4.dist-info/METADATA
aihordeclient-0.4.dist-info/RECORD
