Metadata-Version: 2.4
Name: aihordeclient
Version: 0.4
Summary: AI Horde client to ease creation of plugins
Author: Igor Támara
Author-email: Igor Támara <igor.tamara@gmail.com>
License-Expression: MIT
License-File: LICENSE
Classifier: Programming Language :: Python :: 3
Classifier: Operating System :: OS Independent
Requires-Dist: sseclient-py==1.8.0
Requires-Dist: urllib3==2.2.3
Requires-Python: >=3.8
Project-URL: Homepage, https://github.com/ikks/aihordeclient
Project-URL: Issues, https://github.com/ikks/aihordeclient/issues
